README.md
setup.py
Pydate/__init__.py
Pydate/pydate.py
Pydate/Exceptions/PyDateErrors.py
Pydate/Exceptions/__init__.py
pydater.egg-info/PKG-INFO
pydater.egg-info/SOURCES.txt
pydater.egg-info/dependency_links.txt
pydater.egg-info/requires.txt
pydater.egg-info/top_level.txt