Metadata-Version: 2.1
Name: pydater
Version: 1.0.9
Summary: Basic program and file updater for Github
Home-page: https://github.com/Arif-Helmsys
Author: Helmsys
Author-email: arif.c20e@gmail.com
License: MIT
Keywords: update,auto update,updater
Platform: UNKNOWN
Classifier: Operating System :: Microsoft :: Windows :: Windows 10
Classifier: Programming Language :: Python :: 3.9
